{
  "acknowledgments": [
    {
      "person": "Jihad Hassan - Marketing Director",
      "link": "",
      "note": "Thank you for all the advice and feedback."
    },
    {
      "person": "Colorpong - Artist",
      "link": "ttps://www.youworkforthem.com/designer/536/colorpong?aff=1115",
      "note": "Checkout their amazing vector illustrations."
    },
    {
      "person": "Brittany Chiang - Software Engineer",
      "link": "https://brittanychiang.com/",
      "note": "A major inspiration to create an open source theme."
    },
    {
      "person": "Vercel - Platform",
      "link": "https://vercel.com/docs",
      "note": "Host your own Next.js project for free!"
    }
  ],

  "links": [
    {
      "person": "Privacy Policy",
      "link": "https://euiwonkim11.wixsite.com/chat-ai/privacy",
      "note": ""
    },
    {
      "person": "Terms of Service",
      "link": "https://euiwonkim11.wixsite.com/chat-ai/terms",
      "note": ""
    }
  ],

  "social": [
    {
      "url": "https://medium.com/@--andrewnelson",
      "icon": "medium"
    },
    {
      "url": "https://dev.to/andrewnelson",
      "icon": "dev"
    },
    {
      "url": "https://www.linkedin.com/in/--andrewnelson/",
      "icon": "linkedin"
    },
    {
      "url": "https://github.com/atlamors",
      "icon": "github"
    }
  ]
}
